ideep4py/__init__.py
ideep4py/_ideep4py.so
ideep4py/_version.py
ideep4py/lib/libiomp5.so
ideep4py/lib/libmkldnn.so
ideep4py/lib/libmkldnn.so.0
ideep4py/lib/libmkldnn.so.0.14.0
ideep4py/lib/libmklml_intel.so
ideep4py-2.0.0.post3.dist-info/DESCRIPTION.rst
ideep4py-2.0.0.post3.dist-info/METADATA
ideep4py-2.0.0.post3.dist-info/RECORD
ideep4py-2.0.0.post3.dist-info/WHEEL
ideep4py-2.0.0.post3.dist-info/metadata.json
ideep4py-2.0.0.post3.dist-info/top_level.txt
