Metadata-Version: 2.0
Name: ideep4py
Version: 2.0.0.post3
Summary: ideep4py is a wrapper for iDeep library.
Home-page: https://github.com/intel/ideep
Author: Intel
Author-email: UNKNOWN
License: MIT License
Platform: UNKNOWN
